[{"line":1,"elements":[{"line":3,"name":"","description":"","type":"background","keyword":"Background","steps":[{"result":{"duration":999600,"status":"passed"},"before":[{"result":{"duration":997900,"status":"passed"},"match":{"location":"stepDefinitions.HookExample.beforeStep()"}}],"line":4,"name":"The user is in the uber landing page","match":{"location":"stepDefinitions.TagsExample.the_user_is_in_the_uber_landing_page()"},"after":[{"result":{"duration":1003100,"status":"passed"},"match":{"location":"stepDefinitions.HookExample.afterStep()"}}],"keyword":"Given "}]},{"start_timestamp":"2025-03-20T08:44:04.575Z","before":[{"result":{"duration":5998000,"status":"passed"},"match":{"location":"stepDefinitions.HookExample.beforeSmokeTest()"}}],"line":7,"name":"Check if the user is able to view the uber website","description":"","id":"check-if-the-uber-website-is-functionally-working;check-if-the-user-is-able-to-view-the-uber-website","after":[{"result":{"status":"passed"},"match":{"location":"stepDefinitions.HookExample.afterSmokeTest()"}}],"type":"scenario","keyword":"Scenario","steps":[{"result":{"duration":1010600,"status":"passed"},"before":[{"result":{"status":"passed"},"match":{"location":"stepDefinitions.HookExample.beforeStep()"}}],"line":8,"name":"verify the page title and url","match":{"location":"stepDefinitions.TagsExample.verify_the_page_title_and_url()"},"after":[{"result":{"duration":1000200,"status":"passed"},"match":{"location":"stepDefinitions.HookExample.afterStep()"}}],"keyword":"Then "}],"tags":[{"name":"@SmokeTest"},{"name":"@RegressionTest"},{"name":"@ChromeBrowser"}]},{"line":3,"name":"","description":"","type":"background","keyword":"Background","steps":[{"result":{"status":"passed"},"before":[{"result":{"duration":998400,"status":"passed"},"match":{"location":"stepDefinitions.HookExample.beforeStep()"}}],"line":4,"name":"The user is in the uber landing page","match":{"location":"stepDefinitions.TagsExample.the_user_is_in_the_uber_landing_page()"},"after":[{"result":{"status":"passed"},"match":{"location":"stepDefinitions.HookExample.afterStep()"}}],"keyword":"Given "}]},{"start_timestamp":"2025-03-20T08:44:04.682Z","before":[{"result":{"duration":1000600,"status":"passed"},"match":{"location":"stepDefinitions.HookExample.beforeSmokeTest()"}}],"line":11,"name":"Check if the user is able to search for any cabs","description":"","id":"check-if-the-uber-website-is-functionally-working;check-if-the-user-is-able-to-search-for-any-cabs","after":[{"result":{"status":"passed"},"match":{"location":"stepDefinitions.HookExample.afterSmokeTest()"}}],"type":"scenario","keyword":"Scenario","steps":[{"result":{"duration":998500,"status":"passed"},"before":[{"result":{"duration":1000100,"status":"passed"},"match":{"location":"stepDefinitions.HookExample.beforeStep()"}}],"line":12,"name":"The user enters source and destination location","match":{"location":"stepDefinitions.TagsExample.the_user_enters_source_and_destination_location()"},"after":[{"result":{"status":"passed"},"match":{"location":"stepDefinitions.HookExample.afterStep()"}}],"keyword":"When "},{"result":{"status":"passed"},"before":[{"result":{"status":"passed"},"match":{"location":"stepDefinitions.HookExample.beforeStep()"}}],"line":13,"name":"click on search prices","match":{"location":"stepDefinitions.TagsExample.click_on_search_prices()"},"after":[{"result":{"status":"passed"},"match":{"location":"stepDefinitions.HookExample.afterStep()"}}],"keyword":"Then "},{"result":{"status":"passed"},"before":[{"result":{"status":"passed"},"match":{"location":"stepDefinitions.HookExample.beforeStep()"}}],"line":14,"name":"check if the cab details are displayed","match":{"location":"stepDefinitions.TagsExample.check_if_the_cab_details_are_displayed()"},"after":[{"result":{"status":"passed"},"match":{"location":"stepDefinitions.HookExample.afterStep()"}}],"keyword":"Then "}],"tags":[{"name":"@SmokeTest"},{"name":"@RegressionTest"},{"name":"@BookCab"}]},{"line":3,"name":"","description":"","type":"background","keyword":"Background","steps":[{"result":{"status":"passed"},"before":[{"result":{"duration":997500,"status":"passed"},"match":{"location":"stepDefinitions.HookExample.beforeStep()"}}],"line":4,"name":"The user is in the uber landing page","match":{"location":"stepDefinitions.TagsExample.the_user_is_in_the_uber_landing_page()"},"after":[{"result":{"duration":998900,"status":"passed"},"match":{"location":"stepDefinitions.HookExample.afterStep()"}}],"keyword":"Given "}]},{"start_timestamp":"2025-03-20T08:44:04.740Z","before":[{"result":{"duration":1001300,"status":"passed"},"match":{"location":"stepDefinitions.HookExample.beforeSmokeTest()"}}],"line":17,"name":"Check if the user is able to login to the app","description":"","id":"check-if-the-uber-website-is-functionally-working;check-if-the-user-is-able-to-login-to-the-app","after":[{"result":{"status":"passed"},"match":{"location":"stepDefinitions.HookExample.afterSmokeTest()"}}],"type":"scenario","keyword":"Scenario","steps":[{"result":{"duration":999900,"status":"passed"},"before":[{"result":{"duration":999400,"status":"passed"},"match":{"location":"stepDefinitions.HookExample.beforeStep()"}}],"line":18,"name":"The user on login link","match":{"location":"stepDefinitions.TagsExample.the_user_on_login_link()"},"after":[{"result":{"duration":998900,"status":"passed"},"match":{"location":"stepDefinitions.HookExample.afterStep()"}}],"keyword":"When "},{"result":{"status":"passed"},"before":[{"result":{"status":"passed"},"match":{"location":"stepDefinitions.HookExample.beforeStep()"}}],"line":19,"name":"The user should be taken to the login section","match":{"location":"stepDefinitions.TagsExample.the_user_should_be_taken_to_the_login_section()"},"after":[{"result":{"status":"passed"},"match":{"location":"stepDefinitions.HookExample.afterStep()"}}],"keyword":"Then "}],"tags":[{"name":"@SmokeTest"},{"name":"@RegressionTest"},{"name":"@ChromeBrowser"}]},{"line":3,"name":"","description":"","type":"background","keyword":"Background","steps":[{"result":{"duration":998500,"status":"passed"},"before":[{"result":{"duration":1000700,"status":"passed"},"match":{"location":"stepDefinitions.HookExample.beforeStep()"}}],"line":4,"name":"The user is in the uber landing page","match":{"location":"stepDefinitions.TagsExample.the_user_is_in_the_uber_landing_page()"},"after":[{"result":{"duration":999600,"status":"passed"},"match":{"location":"stepDefinitions.HookExample.afterStep()"}}],"keyword":"Given "}]},{"start_timestamp":"2025-03-20T08:44:04.779Z","line":22,"name":"Check if the user is able to complete payment with VISA card","description":"","id":"check-if-the-uber-website-is-functionally-working;check-if-the-user-is-able-to-complete-payment-with-visa-card","type":"scenario","keyword":"Scenario","steps":[{"result":{"status":"passed"},"before":[{"result":{"status":"passed"},"match":{"location":"stepDefinitions.HookExample.beforeStep()"}}],"line":23,"name":"The user completes the ride","match":{"location":"stepDefinitions.TagsExample.the_user_completes_the_ride()"},"after":[{"result":{"status":"passed"},"match":{"location":"stepDefinitions.HookExample.afterStep()"}}],"keyword":"When "},{"result":{"duration":999800,"status":"passed"},"before":[{"result":{"status":"passed"},"match":{"location":"stepDefinitions.HookExample.beforeStep()"}}],"line":24,"name":"Check if the user is able to complete the payment with VISA","match":{"location":"stepDefinitions.TagsExample.check_if_the_user_is_able_to_complete_the_payment_with_visa()"},"after":[{"result":{"duration":998900,"status":"passed"},"match":{"location":"stepDefinitions.HookExample.afterStep()"}}],"keyword":"Then "}],"tags":[{"name":"@RegressionTest"},{"name":"@BookCab"},{"name":"@ChromeBrowser"}]},{"line":3,"name":"","description":"","type":"background","keyword":"Background","steps":[{"result":{"status":"passed"},"before":[{"result":{"status":"passed"},"match":{"location":"stepDefinitions.HookExample.beforeStep()"}}],"line":4,"name":"The user is in the uber landing page","match":{"location":"stepDefinitions.TagsExample.the_user_is_in_the_uber_landing_page()"},"after":[{"result":{"status":"passed"},"match":{"location":"stepDefinitions.HookExample.afterStep()"}}],"keyword":"Given "}]},{"start_timestamp":"2025-03-20T08:44:04.829Z","line":27,"name":"Check if the user is able to update the language","description":"","id":"check-if-the-uber-website-is-functionally-working;check-if-the-user-is-able-to-update-the-language","type":"scenario","keyword":"Scenario","steps":[{"result":{"duration":2000000,"status":"passed"},"before":[{"result":{"status":"passed"},"match":{"location":"stepDefinitions.HookExample.beforeStep()"}}],"line":28,"name":"The user click on \"EN\" language switch option","match":{"arguments":[{"val":"\"EN\"","offset":18}],"location":"stepDefinitions.TagsExample.the_user_click_on_language_switch_option(java.lang.String)"},"after":[{"result":{"status":"passed"},"match":{"location":"stepDefinitions.HookExample.afterStep()"}}],"keyword":"When "},{"result":{"duration":999300,"status":"passed"},"before":[{"result":{"status":"passed"},"match":{"location":"stepDefinitions.HookExample.beforeStep()"}}],"line":29,"name":"The user should be able to select language","match":{"location":"stepDefinitions.TagsExample.the_user_should_be_able_to_select_language()"},"after":[{"result":{"status":"passed"},"match":{"location":"stepDefinitions.HookExample.afterStep()"}}],"keyword":"Then "}],"tags":[{"name":"@RegressionTest"},{"name":"@ChromeBrowser"}]}],"name":"Check if the uber website is functionally working","description":"","id":"check-if-the-uber-website-is-functionally-working","keyword":"Feature","uri":"file:src/feature/TagExample.feature","tags":[]}]